setup.py
pshub/__init__.py
pshub.egg-info/PKG-INFO
pshub.egg-info/SOURCES.txt
pshub.egg-info/dependency_links.txt
pshub.egg-info/requires.txt
pshub.egg-info/top_level.txt
pshub/matchingengine/__init__.py
pshub/matchingengine/rule.py
pshub/networking/__init__.py
pshub/networking/hub.py
pshub/networking/protocol.py
pshub/networking/pub.py
pshub/networking/sub.py