Metadata-Version: 1.1
Name: pshub
Version: 0.0.2
Summary: A Pub/Sub framework implemented in Python
Home-page: https://github.com/caizixian/pshub
Author: Ivan Cai, lwher
Author-email: caizixian@users.noreply.github.com, 751276936@qq.com
License: AGPLv3
Keywords: asyncio pub sub
Platform: UNKNOWN
Classifier: Development Status :: 2 - Pre-Alpha
Classifier: Intended Audience :: Developers
Classifier: License :: OSI Approved :: GNU Affero General Public License v3
Classifier: Programming Language :: Python :: 3 :: Only
Classifier: Programming Language :: Python :: 3.5
Classifier: Programming Language :: Python :: 3.6
